pyautowebapi/__init__.py
pyautowebapi/api.py
PyAutoWebAPI-0.0.1.dist-info/METADATA
PyAutoWebAPI-0.0.1.dist-info/WHEEL
PyAutoWebAPI-0.0.1.dist-info/top_level.txt
PyAutoWebAPI-0.0.1.dist-info/RECORD
