Metadata-Version: 2.1
Name: PyAutoWebAPI
Version: 0.0.1
Summary: A simple way to call APIs from Python
Home-page: https://github.com/NathanDai5287/PyAutoWebAPI
Author: Nathan Dai
Author-email: nathandai2000@gmail.com
License: MIT
Download-URL: https://pypi.org/project/pyautowebapi/
Keywords: API,PyAutoWebAPI,web API
Platform: UNKNOWN
Requires-Dist: requests
